pipebit/__init__.py
pipebit/initial_config.py
pipebit/safereceiver.py
pipebit/safesender.py
pipebit-0.0.41.dist-info/LICENSE
pipebit-0.0.41.dist-info/METADATA
pipebit-0.0.41.dist-info/WHEEL
pipebit-0.0.41.dist-info/top_level.txt
pipebit-0.0.41.dist-info/RECORD
