Metadata-Version: 2.1
Name: pipebit
Version: 0.0.41
Summary: PipeBit
Home-page: UNKNOWN
Author: Juan Carlos Juárez
Author-email: <jc.juarezgarcia@outlook.com>
License: UNKNOWN
Keywords: Pipelines,Python,Tool
Platform: UNKNOWN
Classifier: Development Status :: 1 - Planning
Classifier: Intended Audience :: Developers
Classifier: Programming Language :: Python :: 3
Classifier: Operating System :: Unix
Classifier: Operating System :: MacOS :: MacOS X
Classifier: Operating System :: Microsoft :: Windows
License-File: LICENSE
